headgen/__init__.py
headgen/__main__.py
headgen/controller.py
headgen/file_filter.py
headgen/file_worker.py
headgen/helper_visitor.py
headgen/key_parser.py
headgen/maker.py
headgen/run.py
headgen/string_worker.py
headgen/visitor.py
headgen-2.3.4.dist-info/LICENSE.txt
headgen-2.3.4.dist-info/METADATA
headgen-2.3.4.dist-info/WHEEL
headgen-2.3.4.dist-info/top_level.txt
headgen-2.3.4.dist-info/RECORD
