Metadata-Version: 2.1
Name: headgen
Version: 2.3.4
Summary: UNKNOWN
Home-page: https://github.com/YoungMeatBoy/headgen.git
Author: Miasnenko Dmitry
Author-email: d2ms2nk@gmail.com
License: UNKNOWN
Platform: UNKNOWN
Requires-Dist: ansicolors
Requires-Dist: colorama
